bytewax/bytewax_azure_ai_search/__init__.py
bytewax/bytewax_azure_ai_search/operators.py
bytewax/bytewax_azure_ai_search/py.typed
bytewax_azure_ai_search-0.2.8.dist-info/LICENSE.md
bytewax_azure_ai_search-0.2.8.dist-info/METADATA
bytewax_azure_ai_search-0.2.8.dist-info/WHEEL
bytewax_azure_ai_search-0.2.8.dist-info/top_level.txt
bytewax_azure_ai_search-0.2.8.dist-info/RECORD
