Metadata-Version: 2.1
Name: bytewax-azure-ai-search
Version: 0.2.8
Summary: Custom sink for Azure AI Search
Author-email: "Bytewax, Inc." <info@bytewax.io>
License: # Software License Agreement
Project-URL: Homepage, https://github.com/bytewax/bytewax-azure-ai-search
Project-URL: Bug Reports, https://github.com/bytewax/bytewax-azure-ai-search/issues/new
Project-URL: Source, https://github.com/bytewax/bytewax-azure-ai-search/
Keywords: bytewax,streaming,operator
Classifier: Development Status :: 4 - Beta
Classifier: Intended Audience :: Developers
Classifier: Programming Language :: Python :: 3
Classifier: Programming Language :: Python :: 3.9
Classifier: Programming Language :: Python :: 3.10
Classifier: Programming Language :: Python :: 3.11
Classifier: Programming Language :: Python :: 3.12
Classifier: Programming Language :: Python :: 3 :: Only
Requires-Python: >=3.9
License-File: LICENSE.md
Requires-Dist: bytewax>=0.21
Requires-Dist: azure-search-documents==11.5.1
Requires-Dist: python-dotenv
Requires-Dist: azure-common==1.1.28
Requires-Dist: azure-core==1.30.2
Requires-Dist: openai==1.34.0
Requires-Dist: ipykernel
Requires-Dist: types-requests
Requires-Dist: haystack-ai==2.2.1
Requires-Dist: trafilatura==1.12.1
